fec_dbsync/__init__.py
fec_dbsync/admin.py
fec_dbsync/apps.py
fec_dbsync/constants.py
fec_dbsync/models.py
fec_dbsync/serializers.py
fec_dbsync/tests.py
fec_dbsync/urls.py
fec_dbsync/utils.py
fec_dbsync/views.py
fec_dbsync/doc-template/api_status_tracking.xlsx
fec_dbsync/doc-template/credit_card_fi.xlsx
fec_dbsync/doc-template/customer_journey_tracking.xlsx
fec_dbsync/doc-template/customer_portfolio.xlsx
fec_dbsync/doc-template/customer_service_tracking.xlsx
fec_dbsync/doc-template/disbursement_status_tracking.xlsx
fec_dbsync/doc-template/loan_health_check.xlsx
fec_dbsync/doc-template/loan_portfolio.xlsx
fec_dbsync/doc-template/loan_snapshot_active.xlsx
fec_dbsync/doc-template/loan_status_tracking.xlsx
fec_dbsync/doc-template/product_performance.xlsx
fec_dbsync/doc-template/reject_loan_application.xlsx
fec_dbsync/doc-template/robo_sales.xlsx
fec_dbsync/management/__init__.py
fec_dbsync/management/commands/__init__.py
fec_dbsync/management/commands/campaign_journey.py
fec_dbsync/management/commands/credit_card_fi.py
fec_dbsync/management/commands/dump.py
fec_dbsync/management/commands/dump2.py
fec_dbsync/management/commands/load_fdv_files.py
fec_dbsync/management/commands/mis_report.py
fec_dbsync/management/commands/post_due.py
fec_dbsync/management/commands/send_notifications.py
fec_dbsync/migrations/0001_initial.py
fec_dbsync/migrations/0002_auto_20180530_2324.py
fec_dbsync/migrations/0003_auto_20180604_0411.py
fec_dbsync/migrations/0004_auto_20180604_1455.py
fec_dbsync/migrations/0005_auto_20180605_2040.py
fec_dbsync/migrations/0006_auto_20180607_2053.py
fec_dbsync/migrations/0007_auto_20180608_0858.py
fec_dbsync/migrations/0008_auto_20180611_0416.py
fec_dbsync/migrations/0009_auto_20180621_0652.py
fec_dbsync/migrations/0010_robocxlview_roboldaview_roboltdview.py
fec_dbsync/migrations/0011_auto_20180712_1039.py
fec_dbsync/migrations/0012_robocollectionfdv.py
fec_dbsync/migrations/0013_auto_20180713_0536.py
fec_dbsync/migrations/0014_auto_20180713_0559.py
labs_integration_fec_dbsync-0.1.10.dist-info/METADATA
labs_integration_fec_dbsync-0.1.10.dist-info/WHEEL
labs_integration_fec_dbsync-0.1.10.dist-info/top_level.txt
labs_integration_fec_dbsync-0.1.10.dist-info/RECORD
